{
  "name": "shrine",
  "type": "gemstone",
  "positions": [
    {
      "x": 608,
      "y": 79,
      "z": 636,
      "action": "VEIN"
    },
    {
      "x": 612,
      "y": 82,
      "z": 628,
      "action": "VEIN"
    },
    {
      "x": 642,
      "y": 83,
      "z": 621,
      "action": "VEIN"
    },
    {
      "x": 644,
      "y": 82,
      "z": 651,
      "action": "VEIN"
    },
    {
      "x": 618,
      "y": 68,
      "z": 658,
      "action": "VEIN"
    },
    {
      "x": 631,
      "y": 63,
      "z": 641,
      "action": "VEIN"
    },
    {
      "x": 613,
      "y": 61,
      "z": 622,
      "action": "VEIN"
    },
    {
      "x": 647,
      "y": 61,
      "z": 624,
      "action": "VEIN"
    },
    {
      "x": 631,
      "y": 62,
      "z": 634,
      "action": "VEIN"
    },
    {
      "x": 617,
      "y": 78,
      "z": 637,
      "action": "VEIN"
    }
  ],
  "targets": []
}